papi/__init__.py
papi/project.py
papi/task.py
papi/user.py
papi/wrappers.py
scripts/__init__.py
scripts/collate_toggl_hours.py
scripts/create_notion_project.py
scripts/create_notion_task.py
scripts/create_project.py
scripts/create_toggl_project.py
papi_projects-0.3.1.dist-info/METADATA
papi_projects-0.3.1.dist-info/WHEEL
papi_projects-0.3.1.dist-info/entry_points.txt
papi_projects-0.3.1.dist-info/RECORD
