Metadata-Version: 2.1
Name: papi-projects
Version: 0.3.1
Summary: PAPI is an API for managing projects
License: MIT
Author: sandyjmacdonald
Author-email: sandyjmacdonald@gmail.com
Requires-Python: >=3.11,<4.0
Classifier: License :: OSI Approved :: MIT License
Classifier: Programming Language :: Python :: 3
Classifier: Programming Language :: Python :: 3.11
Classifier: Programming Language :: Python :: 3.12
Requires-Dist: httpx (>=0.27.2,<0.28.0)
Requires-Dist: pendulum (>=3.0.0,<4.0.0)
Requires-Dist: pyperclip (>=1.9.0,<2.0.0)
Requires-Dist: python-dotenv (>=1.0.0,<2.0.0)
Requires-Dist: tinydb (>=4.8.0,<5.0.0)
